tvbk/__init__.py
tvbk/tvbk_ext.cpython-38-x86_64-linux-gnu.so
tvbk-0.5.dist-info/METADATA
tvbk-0.5.dist-info/WHEEL
tvbk-0.5.dist-info/RECORD
tvbk-0.5.dist-info/licenses/LICENSE
