Metadata-Version: 2.1
Name: tvbk
Version: 0.5
Summary: do virtual brains eat computational popcorn?
Author-Email: Marmaduke Woodman <marmaduke.woodman@univ-amu.fr>
Classifier: License :: OSI Approved :: BSD License
Project-URL: Homepage, https://github.com/maedoc/tvbk
Requires-Python: >=3.8
Requires-Dist: numpy
